shinypkg/__about__.py
shinypkg/__init__.py
shinypkg/_git.py
shinypkg/_pack.py
shinypkg/_template.py
shinypkg/cli.py
shinypkg/templates/.gitignore.j2
shinypkg/templates/README.md.j2
shinypkg/templates/__init__.py.j2
shinypkg/templates/__main__.py.j2
shinypkg/templates/_util.py.j2
shinypkg/templates/app.py.j2
shinypkg/templates/pyproject.toml.j2
shinypkg-0.2.0.dist-info/METADATA
shinypkg-0.2.0.dist-info/WHEEL
shinypkg-0.2.0.dist-info/entry_points.txt
shinypkg-0.2.0.dist-info/licenses/LICENSE
shinypkg-0.2.0.dist-info/RECORD
