Metadata-Version: 2.4
Name: shinypkg
Version: 0.2.0
Summary: A small tool to help you distribute a Shiny app
Author-email: Kenji Sato <mail@kenjisato.jp>
License: MIT
License-File: LICENSE
Requires-Python: >=3.10
Requires-Dist: jinja2>=3.1.0
Requires-Dist: rich>=13.0.0
Requires-Dist: typer>=0.12.3
